AUTHORS
LICENSE
MANIFEST.in
README.rst
setup.py
django_favicon.egg-info/PKG-INFO
django_favicon.egg-info/SOURCES.txt
django_favicon.egg-info/dependency_links.txt
django_favicon.egg-info/not-zip-safe
django_favicon.egg-info/top_level.txt
favicon/__init__.py
favicon/conf.py
favicon/tests.py
favicon/urls.py
favicon/static/favicon.ico